LICENSE
MANIFEST.in
README.rst
setup.py
tests.py
Django_Sites_Lockdown.egg-info/PKG-INFO
Django_Sites_Lockdown.egg-info/SOURCES.txt
Django_Sites_Lockdown.egg-info/dependency_links.txt
Django_Sites_Lockdown.egg-info/requires.txt
Django_Sites_Lockdown.egg-info/top_level.txt
sites_lockdown/__init__.py
sites_lockdown/admin.py
sites_lockdown/models.py