Metadata-Version: 1.0
Name: Django-Sites-Lockdown
Version: 0.0.3
Summary: Remove the ability to add or edit sites in Django's admin panel.
Home-page: https://github.com/RichardOfWard/django-sites-lockdown
Author: Richard Ward
Author-email: richard@richard.ward.name
License: MIT License
Platform: UNKNOWN
